MANIFEST.in
README.md
setup.cfg
setup.py
django_cc_wallet.egg-info/PKG-INFO
django_cc_wallet.egg-info/SOURCES.txt
django_cc_wallet.egg-info/dependency_links.txt
django_cc_wallet.egg-info/requires.txt
django_cc_wallet.egg-info/top_level.txt
wallet/__init__.py
wallet/admin.py
wallet/models.py
wallet/tests.py
wallet/urls.py
wallet/views.py
wallet/migrations/0001_initial.py
wallet/migrations/__init__.py