Metadata-Version: 1.1
Name: django-cc-wallet
Version: 0.0.1
Summary: Example of django-cc wallet for Bitcoin and other cryptocurrencies
Home-page: https://github.com/limpbrains/django-cc-wallet
Author: Ivan Vershigora
Author-email: ivan.vershigora@gmail.com
License: MIT License
Download-URL: https://github.com/limpbrains/django-cc-wallet/tarball/0.0.1
Keywords: bitcoin litecoin django django-cc wallet
Platform: UNKNOWN
